{
  "__inputs": [
    {
      "name": "DS_PROMETHEUS",
      "label": "Prometheus",
      "description": "",
      "type": "datasource",
      "pluginId": "prometheus",
      "pluginName": "Prometheus"
    }
  ],
  "__requires": [
    {
      "type": "grafana",
      "id": "grafana",
      "name": "Grafana",
      "version": "11.1.0"
    },
    {
      "type": "datasource",
      "id": "prometheus",
      "name": "Prometheus",
      "version": "1.0.0"
    }
  ],
  "annotations": {
    "list": [
      {
        "builtIn": 1,
        "datasource": {
          "type": "grafana",
          "uid": "-- Grafana --"
        },
        "enable": true,
        "hide": true,
        "iconColor": "rgba(0, 211, 255, 1)",
        "name": "Annotations & Alerts",
        "type": "dashboard"
      }
    ]
  },
  "description": "Per-queue depth and message flow for the OpenStack message bus: which queues are deepest, which have no consumers, and whether publish rate is outrunning delivery. Answers \"which agent stopped consuming?\" — the usual root cause of a RabbitMQ backlog that eventually blocks the whole control plane.",
  "editable": true,
  "fiscalYearStartMonth": 0,
  "graphTooltip": 1,
  "id": null,
  "links": [],
  "liveNow": false,
  "panels": [
    {
      "id": 1,
      "type": "row",
      "title": "Backlog hot spots — read these first",
      "collapsed": false,
      "gridPos": {
        "h": 1,
        "w": 24,
        "x": 0,
        "y": 0
      },
      "panels": []
    },
    {
      "type": "stat",
      "title": "Queues with no consumers (and backlog)",
      "description": "Queues holding ready messages but with zero consumers — each one is very likely a dead OpenStack agent.",
      "fieldConfig": {
        "defaults": {
          "color": {
            "mode": "thresholds"
          },
          "mappings": [],
          "thresholds": {
            "mode": "absolute",
            "steps": [
              {
                "color": "green",
                "value": null
              },
              {
                "color": "red",
                "value": 1
              }
            ]
          },
          "unit": "short",
          "decimals": 0
        },
        "overrides": []
      },
      "options": {
        "reduceOptions": {
          "calcs": [
            "lastNotNull"
          ],
          "fields": "",
          "values": false
        },
        "orientation": "auto",
        "textMode": "auto",
        "colorMode": "background",
        "graphMode": "area",
        "justifyMode": "auto",
        "showPercentChange": false
      },
      "datasource": {
        "type": "prometheus",
        "uid": "${DS_PROMETHEUS}"
      },
      "targets": [
        {
          "datasource": {
            "type": "prometheus",
            "uid": "${DS_PROMETHEUS}"
          },
          "editorMode": "code",
          "expr": "count(\n  (rabbitmq_queue_messages_ready{job=\"$job\", vhost=~\"$vhost\"} > 0)\n  and (rabbitmq_queue_consumers{job=\"$job\", vhost=~\"$vhost\"} == 0)\n) or vector(0)",
          "instant": true,
          "range": false,
          "legendFormat": "starved",
          "refId": "A"
        }
      ],
      "id": 2,
      "gridPos": {
        "h": 8,
        "w": 6,
        "x": 0,
        "y": 1
      }
    },
    {
      "type": "stat",
      "title": "Deepest queue",
      "description": "Largest single-queue backlog (ready messages). Drill into the table below to name it.",
      "fieldConfig": {
        "defaults": {
          "color": {
            "mode": "thresholds"
          },
          "mappings": [],
          "thresholds": {
            "mode": "absolute",
            "steps": [
              {
                "color": "green",
                "value": null
              },
              {
                "color": "yellow",
                "value": 1000
              },
              {
                "color": "red",
                "value": 10000
              }
            ]
          },
          "unit": "short",
          "decimals": 0
        },
        "overrides": []
      },
      "options": {
        "reduceOptions": {
          "calcs": [
            "lastNotNull"
          ],
          "fields": "",
          "values": false
        },
        "orientation": "auto",
        "textMode": "auto",
        "colorMode": "value",
        "graphMode": "area",
        "justifyMode": "auto",
        "showPercentChange": false
      },
      "datasource": {
        "type": "prometheus",
        "uid": "${DS_PROMETHEUS}"
      },
      "targets": [
        {
          "datasource": {
            "type": "prometheus",
            "uid": "${DS_PROMETHEUS}"
          },
          "editorMode": "code",
          "expr": "max(rabbitmq_queue_messages_ready{job=\"$job\", vhost=~\"$vhost\"}) or vector(0)",
          "instant": true,
          "range": false,
          "legendFormat": "max ready",
          "refId": "A"
        }
      ],
      "id": 3,
      "gridPos": {
        "h": 8,
        "w": 6,
        "x": 6,
        "y": 1
      }
    },
    {
      "type": "stat",
      "title": "Total ready",
      "description": "Cluster-wide messages ready for delivery (not yet picked up by a consumer).",
      "fieldConfig": {
        "defaults": {
          "color": {
            "mode": "thresholds"
          },
          "mappings": [],
          "thresholds": {
            "mode": "absolute",
            "steps": [
              {
                "color": "green",
                "value": null
              }
            ]
          },
          "unit": "short",
          "decimals": 0
        },
        "overrides": []
      },
      "options": {
        "reduceOptions": {
          "calcs": [
            "lastNotNull"
          ],
          "fields": "",
          "values": false
        },
        "orientation": "auto",
        "textMode": "auto",
        "colorMode": "value",
        "graphMode": "area",
        "justifyMode": "auto",
        "showPercentChange": false
      },
      "datasource": {
        "type": "prometheus",
        "uid": "${DS_PROMETHEUS}"
      },
      "targets": [
        {
          "datasource": {
            "type": "prometheus",
            "uid": "${DS_PROMETHEUS}"
          },
          "editorMode": "code",
          "expr": "sum(rabbitmq_queue_messages_ready{job=\"$job\", vhost=~\"$vhost\"}) or vector(0)",
          "instant": true,
          "range": false,
          "legendFormat": "ready",
          "refId": "A"
        }
      ],
      "id": 4,
      "gridPos": {
        "h": 8,
        "w": 6,
        "x": 12,
        "y": 1
      }
    },
    {
      "type": "stat",
      "title": "Total unacknowledged",
      "description": "Messages delivered but not yet acked. A large persistent value means consumers are stuck mid-processing.",
      "fieldConfig": {
        "defaults": {
          "color": {
            "mode": "thresholds"
          },
          "mappings": [],
          "thresholds": {
            "mode": "absolute",
            "steps": [
              {
                "color": "green",
                "value": null
              },
              {
                "color": "yellow",
                "value": 1000
              },
              {
                "color": "red",
                "value": 10000
              }
            ]
          },
          "unit": "short",
          "decimals": 0
        },
        "overrides": []
      },
      "options": {
        "reduceOptions": {
          "calcs": [
            "lastNotNull"
          ],
          "fields": "",
          "values": false
        },
        "orientation": "auto",
        "textMode": "auto",
        "colorMode": "value",
        "graphMode": "area",
        "justifyMode": "auto",
        "showPercentChange": false
      },
      "datasource": {
        "type": "prometheus",
        "uid": "${DS_PROMETHEUS}"
      },
      "targets": [
        {
          "datasource": {
            "type": "prometheus",
            "uid": "${DS_PROMETHEUS}"
          },
          "editorMode": "code",
          "expr": "sum(rabbitmq_queue_messages_unacknowledged{job=\"$job\", vhost=~\"$vhost\"}) or vector(0)",
          "instant": true,
          "range": false,
          "legendFormat": "unacked",
          "refId": "A"
        }
      ],
      "id": 5,
      "gridPos": {
        "h": 8,
        "w": 6,
        "x": 18,
        "y": 1
      }
    },
    {
      "id": 6,
      "type": "row",
      "title": "Deepest queues",
      "collapsed": false,
      "gridPos": {
        "h": 1,
        "w": 24,
        "x": 0,
        "y": 9
      },
      "panels": []
    },
    {
      "type": "bargauge",
      "title": "Top 10 queues by ready messages",
      "description": "The ten queues with the most messages waiting for a consumer. The OpenStack service is usually obvious from the queue name.",
      "fieldConfig": {
        "defaults": {
          "color": {
            "mode": "thresholds"
          },
          "mappings": [],
          "thresholds": {
            "mode": "absolute",
            "steps": [
              {
                "color": "green",
                "value": null
              },
              {
                "color": "yellow",
                "value": 1000
              },
              {
                "color": "red",
                "value": 10000
              }
            ]
          },
          "unit": "short"
        },
        "overrides": []
      },
      "options": {
        "reduceOptions": {
          "calcs": [
            "lastNotNull"
          ],
          "fields": "",
          "values": false
        },
        "orientation": "horizontal",
        "displayMode": "gradient",
        "valueMode": "color",
        "showUnfilled": true,
        "minVizWidth": 0,
        "minVizHeight": 10
      },
      "datasource": {
        "type": "prometheus",
        "uid": "${DS_PROMETHEUS}"
      },
      "targets": [
        {
          "datasource": {
            "type": "prometheus",
            "uid": "${DS_PROMETHEUS}"
          },
          "editorMode": "code",
          "expr": "topk(10, rabbitmq_queue_messages_ready{job=\"$job\", vhost=~\"$vhost\"})",
          "instant": true,
          "range": false,
          "legendFormat": "{{queue}}",
          "refId": "A"
        }
      ],
      "id": 7,
      "gridPos": {
        "h": 8,
        "w": 12,
        "x": 0,
        "y": 10
      }
    },
    {
      "type": "table",
      "title": "Queues with no consumers",
      "description": "Every queue that has a backlog but no consumer attached — the shortlist of agents to restart.",
      "fieldConfig": {
        "defaults": {
          "color": {
            "mode": "thresholds"
          },
          "mappings": [],
          "thresholds": {
            "mode": "absolute",
            "steps": [
              {
                "color": "green",
                "value": null
              }
            ]
          },
          "unit": "short",
          "custom": {
            "align": "auto",
            "cellOptions": {
              "type": "auto"
            },
            "inspect": false,
            "filterable": true
          }
        },
        "overrides": []
      },
      "options": {
        "showHeader": true,
        "cellHeight": "sm",
        "footer": {
          "show": false,
          "reducer": [
            "sum"
          ],
          "countRows": false,
          "fields": ""
        },
        "sortBy": []
      },
      "datasource": {
        "type": "prometheus",
        "uid": "${DS_PROMETHEUS}"
      },
      "targets": [
        {
          "datasource": {
            "type": "prometheus",
            "uid": "${DS_PROMETHEUS}"
          },
          "editorMode": "code",
          "expr": "(rabbitmq_queue_messages_ready{job=\"$job\", vhost=~\"$vhost\"} > 0) and (rabbitmq_queue_consumers{job=\"$job\", vhost=~\"$vhost\"} == 0)",
          "instant": true,
          "range": false,
          "legendFormat": "{{queue}}",
          "refId": "A",
          "format": "table"
        }
      ],
      "transformations": [
        {
          "id": "organize",
          "options": {
            "renameByName": {
              "queue": "Queue",
              "vhost": "Vhost",
              "Value": "Ready"
            }
          }
        }
      ],
      "id": 8,
      "gridPos": {
        "h": 8,
        "w": 12,
        "x": 12,
        "y": 10
      }
    },
    {
      "id": 9,
      "type": "row",
      "title": "Flow — publish vs deliver",
      "collapsed": false,
      "gridPos": {
        "h": 1,
        "w": 24,
        "x": 0,
        "y": 18
      },
      "panels": []
    },
    {
      "type": "timeseries",
      "title": "Publish vs deliver rate",
      "description": "Cluster-wide publish rate against delivery rate. When publish sits above deliver, the backlog is building.",
      "fieldConfig": {
        "defaults": {
          "color": {
            "mode": "palette-classic"
          },
          "mappings": [],
          "thresholds": {
            "mode": "absolute",
            "steps": [
              {
                "color": "green",
                "value": null
              }
            ]
          },
          "unit": "ops",
          "min": 0,
          "custom": {
            "drawStyle": "line",
            "lineInterpolation": "linear",
            "lineWidth": 1,
            "fillOpacity": 10,
            "gradientMode": "none",
            "spanNulls": false,
            "showPoints": "never",
            "pointSize": 5,
            "stacking": {
              "mode": "none",
              "group": "A"
            },
            "axisPlacement": "auto",
            "axisLabel": "",
            "scaleDistribution": {
              "type": "linear"
            },
            "axisCenteredZero": false,
            "hideFrom": {
              "tooltip": false,
              "viz": false,
              "legend": false
            },
            "thresholdsStyle": {
              "mode": "off"
            }
          }
        },
        "overrides": []
      },
      "options": {
        "legend": {
          "showLegend": true,
          "displayMode": "table",
          "placement": "bottom",
          "calcs": [
            "lastNotNull",
            "max",
            "mean"
          ]
        },
        "tooltip": {
          "mode": "multi",
          "sort": "desc"
        }
      },
      "datasource": {
        "type": "prometheus",
        "uid": "${DS_PROMETHEUS}"
      },
      "targets": [
        {
          "datasource": {
            "type": "prometheus",
            "uid": "${DS_PROMETHEUS}"
          },
          "editorMode": "code",
          "expr": "sum(rate(rabbitmq_queue_messages_published_total{job=\"$job\", vhost=~\"$vhost\"}[5m]))",
          "instant": false,
          "range": true,
          "legendFormat": "published/s",
          "refId": "A"
        },
        {
          "datasource": {
            "type": "prometheus",
            "uid": "${DS_PROMETHEUS}"
          },
          "editorMode": "code",
          "expr": "sum(rate(rabbitmq_queue_messages_delivered_total{job=\"$job\", vhost=~\"$vhost\"}[5m]))",
          "instant": false,
          "range": true,
          "legendFormat": "delivered/s",
          "refId": "B"
        }
      ],
      "id": 10,
      "gridPos": {
        "h": 8,
        "w": 12,
        "x": 0,
        "y": 19
      }
    },
    {
      "type": "timeseries",
      "title": "Fastest-growing queues",
      "description": "Per-queue rate of change of ready messages (top 10). Positive and climbing means that queue is falling behind.",
      "fieldConfig": {
        "defaults": {
          "color": {
            "mode": "palette-classic"
          },
          "mappings": [],
          "thresholds": {
            "mode": "absolute",
            "steps": [
              {
                "color": "green",
                "value": null
              }
            ]
          },
          "unit": "ops",
          "custom": {
            "drawStyle": "line",
            "lineInterpolation": "linear",
            "lineWidth": 1,
            "fillOpacity": 10,
            "gradientMode": "none",
            "spanNulls": false,
            "showPoints": "never",
            "pointSize": 5,
            "stacking": {
              "mode": "none",
              "group": "A"
            },
            "axisPlacement": "auto",
            "axisLabel": "",
            "scaleDistribution": {
              "type": "linear"
            },
            "axisCenteredZero": false,
            "hideFrom": {
              "tooltip": false,
              "viz": false,
              "legend": false
            },
            "thresholdsStyle": {
              "mode": "off"
            }
          }
        },
        "overrides": []
      },
      "options": {
        "legend": {
          "showLegend": true,
          "displayMode": "table",
          "placement": "bottom",
          "calcs": [
            "lastNotNull",
            "max",
            "mean"
          ]
        },
        "tooltip": {
          "mode": "multi",
          "sort": "desc"
        }
      },
      "datasource": {
        "type": "prometheus",
        "uid": "${DS_PROMETHEUS}"
      },
      "targets": [
        {
          "datasource": {
            "type": "prometheus",
            "uid": "${DS_PROMETHEUS}"
          },
          "editorMode": "code",
          "expr": "topk(10, deriv(rabbitmq_queue_messages_ready{job=\"$job\", vhost=~\"$vhost\"}[5m]))",
          "instant": false,
          "range": true,
          "legendFormat": "{{queue}}",
          "refId": "A"
        }
      ],
      "id": 11,
      "gridPos": {
        "h": 8,
        "w": 12,
        "x": 12,
        "y": 19
      }
    }
  ],
  "refresh": "30s",
  "schemaVersion": 39,
  "tags": [
    "openstack",
    "rabbitmq",
    "messaging",
    "queues"
  ],
  "templating": {
    "list": [
      {
        "name": "job",
        "label": "Job",
        "type": "query",
        "hide": 0,
        "description": "Prometheus scrape job for your RabbitMQ nodes.",
        "datasource": {
          "type": "prometheus",
          "uid": "${DS_PROMETHEUS}"
        },
        "definition": "label_values(rabbitmq_queue_messages_ready, job)",
        "query": {
          "qryType": 1,
          "query": "label_values(rabbitmq_queue_messages_ready, job)",
          "refId": "variable"
        },
        "refresh": 2,
        "regex": "",
        "sort": 1,
        "includeAll": false,
        "allValue": ".*",
        "multi": false,
        "current": {},
        "options": []
      },
      {
        "name": "vhost",
        "label": "Vhost",
        "type": "query",
        "hide": 0,
        "description": "RabbitMQ virtual host (OpenStack usually uses \"/\").",
        "datasource": {
          "type": "prometheus",
          "uid": "${DS_PROMETHEUS}"
        },
        "definition": "label_values(rabbitmq_queue_messages_ready{job=\"$job\"}, vhost)",
        "query": {
          "qryType": 1,
          "query": "label_values(rabbitmq_queue_messages_ready{job=\"$job\"}, vhost)",
          "refId": "variable"
        },
        "refresh": 2,
        "regex": "",
        "sort": 1,
        "includeAll": true,
        "allValue": ".*",
        "multi": true,
        "current": {},
        "options": []
      }
    ]
  },
  "time": {
    "from": "now-6h",
    "to": "now"
  },
  "timepicker": {},
  "timezone": "",
  "title": "OpenStack / RabbitMQ — Queue Depth & Flow",
  "uid": "openstack-rabbitmq-queues",
  "version": 1,
  "weekStart": ""
}
